Metadata-Version: 1.1
Name: iCount
Version: 2.0.0
Summary: Computational pipeline for analysis of iCLIP data
Home-page: https://github.com/tomazc/iCount
Author: University of Ljubljana, Bioinformatics Laboratory
Author-email: tomazc@gmail.com
License: MIT
Keywords: iCLIP protein-RNA
Platform: UNKNOWN
Classifier: Development Status :: 4 - Beta
Classifier: Topic :: Scientific/Engineering :: Bio-Informatics
Classifier: Intended Audience :: Developers
Classifier: Intended Audience :: Science/Research
Classifier: Operating System :: POSIX
Classifier: Programming Language :: Python
Classifier: Programming Language :: Python :: 3
Classifier: Programming Language :: Python :: 3.4
Classifier: Programming Language :: Python :: 3.5
